motifx/__init__.py
motifx/cache.py
motifx/motifx.py
motifx/operator.py
motifx-0.0.1.dist-info/LICENSE
motifx-0.0.1.dist-info/METADATA
motifx-0.0.1.dist-info/WHEEL
motifx-0.0.1.dist-info/top_level.txt
motifx-0.0.1.dist-info/RECORD
